mplplot/__init__.py
mplplot/importer.py
mplplot/main.py
mplplot/meta.py
mplplot/network.py
mplplot/plots.py
mplplot/polar.py
mplplot/stacked_bar.py
mplplot/util.py
mplplot-0.1.dist-info/LICENSE.txt
mplplot-0.1.dist-info/METADATA
mplplot-0.1.dist-info/WHEEL
mplplot-0.1.dist-info/top_level.txt
mplplot-0.1.dist-info/RECORD
