Metadata-Version: 2.1
Name: mplplot
Version: 0.1
Summary: matplotlib customizations and customized ploting functions
Home-page: UNKNOWN
Author: Keji Li
Author-email: mail@keji.li
License: UNKNOWN
Platform: UNKNOWN
Requires-Dist: matplotlib
Requires-Dist: numpy
Requires-Dist: seaborn
Provides-Extra: network
Requires-Dist: networkx ; extra == 'network'
